etc/evolve-agent/systemd/evolve-agent.service
etc/evolve-agent/sysvinit/evolve-agent
etc/evolve-agent/upstart/evolve-agent.conf
evolve_agent-1.0.2.data/scripts/evolve-agent
evolve_agent-1.0.2.dist-info/DESCRIPTION.rst
evolve_agent-1.0.2.dist-info/METADATA
evolve_agent-1.0.2.dist-info/RECORD
evolve_agent-1.0.2.dist-info/WHEEL
evolve_agent-1.0.2.dist-info/metadata.json
evolve_agent-1.0.2.dist-info/top_level.txt
evolveagent/__init__.py
evolveagent/iws/__init__.py
evolveagent/iws/caller.py
evolveagent/iws/iwsclient.py
evolveagent/iws/agent/__init__.py
evolveagent/iws/agent/config.py
evolveagent/iws/agent/logger.py
evolveagent/iws/agent/module.py
evolveagent/iws/agent/service.py
