Metadata-Version: 2.0
Name: evolve-agent
Version: 1.0.2
Summary: Evolve Agent to connect your systems to the Evolve Security Automation and Orchestration Platform.
Home-page: https://evolve.threatintelligence.com
Author: Threat Intelligence
Author-email: evolve-pypi@threatintelligence.com
License: MIT
Platform: UNKNOWN
Classifier: Development Status :: 5 - Production/Stable
Classifier: Environment :: Console
Classifier: Intended Audience :: Information Technology
Classifier: Intended Audience :: Other Audience
Classifier: Intended Audience :: System Administrators
Classifier: License :: OSI Approved :: MIT License
Classifier: Natural Language :: English
Classifier: Operating System :: POSIX :: Linux
Classifier: Programming Language :: Python :: 2.7
Classifier: Programming Language :: Python :: 2 :: Only
Classifier: Topic :: Security
Classifier: Topic :: System
Classifier: Topic :: Utilities
Requires-Dist: Pygments (==2.2.0)
Requires-Dist: certifi (==2018.8.13)
Requires-Dist: chardet (==3.0.4)
Requires-Dist: deepdiff (==3.3.0)
Requires-Dist: dpath (==1.4.2)
Requires-Dist: idna (==2.7)
Requires-Dist: jsonpickle (==0.9.6)
Requires-Dist: netaddr (==0.7.19)
Requires-Dist: python-magic (==0.4.15)
Requires-Dist: requests (==2.19.1)
Requires-Dist: requests-file (==1.4.3)
Requires-Dist: schedule (==0.5.0)
Requires-Dist: six (==1.11.0)
Requires-Dist: tldextract (==2.2.0)
Requires-Dist: urllib3 (==1.23)
Requires-Dist: virtualenv (==16.0.0)
